dictools/__init__.py
dictools/tests/__init__.py
dictools/tests/test_dict2dotnotation.py
dictools/tests/test_dict_del_vals.py
dictools/tests/test_get_by_path.py
dictools/tests/test_make_getter.py
dictools-0.1.1.dist-info/LICENSE
dictools-0.1.1.dist-info/METADATA
dictools-0.1.1.dist-info/WHEEL
dictools-0.1.1.dist-info/top_level.txt
dictools-0.1.1.dist-info/RECORD
